<?xml version="1.0" encoding="UTF-8"?>


<themes>
<data xmls="https://raw.githubusercontent.com/SalahTaha13/IOS-StoreTheme/STMods/xml/" walls="https://raw.githubusercontent.com/SalahTaha13/IOS-StoreTheme/STMods/walls/" scs="https://raw.githubusercontent.com/SalahTaha13/IOS-StoreTheme/STMods/screens/"/>



<theme>
<title>IOS_Light</title>
<date>03/01/2022</date>
  </theme>
  <theme>
<title>IOS_Night</title>
<date>03/01/2022</date>
  </theme>
  <theme>
    <title>IOS_Green</title>
    <date>06/01/2022</date> 
  </theme>
  <theme>
    <title>IOS_Cartoon</title>
    <date>06/01/2022</date> 
  </theme>
  <theme>
    <title>IOS_Naruto</title>
    <date>06/01/2022</date>
  </theme>
  <theme>
    <title>IOS_Snoopy</title>
    <date>07/01/2022</date>
    </theme>
  </data>
</themes>
